nebula/cert/__init__.py
nebula/cert/__main__.py
nebula/cert/ca.py
nebula_cert_py-0.3.0.dist-info/entry_points.txt
nebula_cert_py-0.3.0.dist-info/WHEEL
nebula_cert_py-0.3.0.dist-info/METADATA
nebula_cert_py-0.3.0.dist-info/RECORD
