Metadata-Version: 2.1
Name: nebula-cert-py
Version: 0.3.0
Summary: Manage nebula certificates from Python
License: MIT
Author: charbonnierg
Author-email: guillaume.charbonnier@araymond.com
Requires-Python: >=3.7,<4.0
Classifier: License :: OSI Approved :: MIT License
Classifier: Programming Language :: Python :: 3
Classifier: Programming Language :: Python :: 3.7
Classifier: Programming Language :: Python :: 3.8
Classifier: Programming Language :: Python :: 3.9
Classifier: Programming Language :: Python :: 3.10
Requires-Dist: azure-identity (==1.7.1)
Requires-Dist: azure-keyvault-secrets (==4.6.0)
Requires-Dist: click
Requires-Dist: python-dateutil
